{
    "Bed|+05.02|+00.00|-03.38": [
        5.0,
        -4.0,
        180,
        30
    ],
    "Bed|-02.36|+00.00|+04.18": [
        -2.5,
        2.5,
        0,
        30
    ],
    "Cabinet|+00.72|+01.54|-01.58": [
        1.5,
        -2,
        0,
        0
    ],
    "Cabinet|+02.04|+00.37|-03.90": [
        2.75,
        -5.25,
        270,
        30
    ],
    "Cabinet|+02.04|+00.37|-04.69": [
        2.75,
        -5.5,
        270,
        30
    ],
    "Cabinet|-00.52|+01.54|-01.59": [
        1.5,
        -2,
        0,
        0
    ],
    "CoffeeTable|-02.80|00.00|-01.00": [
        -2.75,
        -2.5,
        0,
        30
    ],
    "CounterTop|+06.04|+00.01|-01.02": [
        5.0,
        -1.25,
        90,
        30
    ],
    "CounterTop|+06.35|+00.01|+01.23": [
        5.0,
        0.5,
        90,
        30
    ],
    "Desk|+01.98|+00.00|+01.78": [
        4.0,
        3.0,
        180,
        30
    ],
    "DiningTable|+03.30|00.00|+00.73": [
        3.25,
        0.0,
        0,
        30
    ],
    "Dresser|+05.61|00.00|-02.33": [
        5.0,
        -3.75,
        90,
        30
    ],
    "DressingTable|-02.21|+00.03|+04.53": [
        3.5,
        3.25,
        0,
        30
    ],
    "Fridge|+03.48|+00.00|-02.36": [
        4.75,
        -1.5,
        180,
        0
    ],
    "Microwave|+06.07|+00.94|+00.86": [
        5.0,
        0.75,
        90,
        0
    ],
    "Shelf|+01.54|+00.41|+01.80": [
        4.0,
        3.25,
        180,
        30
    ],
    "Shelf|+01.54|-00.04|+01.80": [
        4.0,
        3.5,
        180,
        30
    ],
    "Shelf|+03.39|+01.22|-01.50": [
        2.5,
        -2.0,
        90,
        30
    ],
    "Shelf|-01.69|+00.30|-05.90": [
        -2.75,
        -4.75,
        270,
        30
    ],
    "Shelf|-01.69|+00.62|-05.90": [
        -2.75,
        -4.75,
        180,
        30
    ],
    "Shelf|-01.69|+00.96|-05.90": [
        -2.75,
        -4.75,
        180,
        30
    ],
    "Shelf|-01.69|+01.29|-05.90": [
        -2.75,
        -4.75,
        180,
        0
    ],
    "Shelf|-01.69|+01.63|-05.90": [
        -2.75,
        -4.75,
        180,
        0
    ],
    "Shelf|-01.69|+01.95|-05.90": [
        -2.75,
        -4.75,
        180,
        30
    ],
    "Shelf|-01.69|+02.25|-05.90": [
        -2.75,
        -4.75,
        180,
        -30
    ],
    "Shelf|-02.41|+00.30|-05.90": [
        -3.75,
        -4.75,
        180,
        30
    ],
    "Shelf|-02.41|+00.62|-05.90": [
        -3.75,
        -4.75,
        180,
        30
    ],
    "Shelf|-02.41|+00.96|-05.90": [
        -3.75,
        -4.75,
        180,
        30
    ],
    "Shelf|-02.41|+01.29|-05.90": [
        -3.75,
        -4.75,
        180,
        30
    ],
    "Shelf|-02.41|+01.63|-05.90": [
        -3.75,
        -4.75,
        180,
        0
    ],
    "Shelf|-02.41|+01.95|-05.90": [
        -3.75,
        -4.75,
        180,
        30
    ],
    "Shelf|-02.41|+02.25|-05.90": [
        -3.75,
        -4.75,
        180,
        -30
    ],
    "Shelf|-02.81|+00.10|-01.00": [
        -1.25,
        -1.5,
        270,
        30
    ],
    "Shelf|-05.21|+00.27|+00.58": [
        -5.0,
        -1.0,
        0,
        30
    ],
    "Shelf|-05.21|+00.78|+00.61": [
        -5,
        -0.75,
        0,
        30
    ],
    "Shelf|-05.21|+01.28|+00.58": [
        -5.0,
        -0.25,
        0,
        30
    ],
    "Shelf|-05.21|+01.81|+00.58": [
        -5.0,
        -0.25,
        0,
        0
    ],
    "sink|+00.89|+00.59|+03.82":[
        0,
        3.5,
        90,
        30
    ],
    "sink|+00.89|+00.59|+03.82|SinkBasin":[
        0,
        3.5,
        90,
        30
    ],
    "Sink|+00.89|+00.59|+03.82":[
        0,
        3.5,
        90,
        30
    ],
    "Sink|+00.89|+00.59|+03.82|SinkBasin":[
        0,
        3.5,
        90,
        30
    ],
    "Sink|+02.22|+00.62|-01.48": [
        2.5,
        -2.0,
        0,
        30
    ],
    "Sink|+02.22|+00.62|-01.48|SinkBasin": [
        2.5,
        -2.0,
        0,
        30
    ],
    "Sink|+05.92|+00.86|-01.27": [
        5.0,
        -1.25,
        90,
        30
    ],
    "Sink|+05.92|+00.86|-01.27|SinkBasin": [
        5.0,
        -1.5,
        90,
        30
    ],
    "Sink|-00.04|+00.84|-01.35|SinkBasin": [
        1.5,
        -1.75,
        270,
        30
    ],
    "Sofa|-02.57|00.00|+00.38": [
        -2.0,
        -0.75,
        0,
        30
    ],
    "Toilet|+03.12|00.00|-02.23": [
        2.25,
        -2.25,
        90,
        30
    ]
}